CHANGELOG
MANIFEST.in
README.md
setup.py
lsl_toolkits/__init__.py
lsl_toolkits/USRP/__init__.py
lsl_toolkits/USRP/common.py
lsl_toolkits/USRP/reader.py
lsl_toolkits_usrp.egg-info/PKG-INFO
lsl_toolkits_usrp.egg-info/SOURCES.txt
lsl_toolkits_usrp.egg-info/dependency_links.txt
lsl_toolkits_usrp.egg-info/namespace_packages.txt
lsl_toolkits_usrp.egg-info/not-zip-safe
lsl_toolkits_usrp.egg-info/requires.txt
lsl_toolkits_usrp.egg-info/top_level.txt
scripts/usrpCheckTimetags.py
scripts/usrpCombinePols.py
scripts/usrpFileCheck.py
scripts/usrpHDFCombinePols.py
scripts/usrpHDFWaterfall.py
scripts/usrpSpectra.py
scripts/usrpTimeseries.py
scripts/usrpWaterfall.py
tests/__init__.py
tests/test_scripts.py
tests/test_usrp.py
tests/data/usrp-test.dat