Metadata-Version: 1.2
Name: lsl-toolkits-usrp
Version: 0.3.0
Summary: LSL Toolkit for URSP Data
Home-page: https://fornax.phys.unm.edu/lwa/trac/
Author: Jayce Dowell
Author-email: jdowell@unm.edu
License: GPL
Platform: UNKNOWN
Classifier: Development Status :: 5 - Production/Stable
Classifier: Intended Audience :: Developers
Classifier: Intended Audience :: Science/Research
Classifier: License :: OSI Approved :: GNU General Public License (GPL)
Classifier: Topic :: Scientific/Engineering :: Astronomy
Classifier: Programming Language :: Python :: 2
Classifier: Programming Language :: Python :: 2.6
Classifier: Programming Language :: Python :: 2.7
Classifier: Operating System :: MacOS :: MacOS X
Classifier: Operating System :: POSIX :: Linux
Requires-Python: >=2.7
